cryo_mcp/__init__.py
cryo_mcp/server.py
cryo_mcp/sql.py
mseep_cryo_mcp-0.1.8.dist-info/licenses/LICENSE
mseep_cryo_mcp-0.1.8.dist-info/METADATA
mseep_cryo_mcp-0.1.8.dist-info/WHEEL
mseep_cryo_mcp-0.1.8.dist-info/entry_points.txt
mseep_cryo_mcp-0.1.8.dist-info/top_level.txt
mseep_cryo_mcp-0.1.8.dist-info/RECORD
