Metadata-Version: 2.4
Name: mseep-cryo-mcp
Version: 0.1.8
Summary: MCP server for querying Ethereum blockchain data using cryo
Author-email: mseep <support@skydeck.ai>
License: MIT License
Project-URL: Homepage, https://github.com/z80dev/cryo-mcp
Project-URL: Bug Tracker, https://github.com/z80dev/cryo-mcp/issues
Keywords: ethereum,blockchain,cryo,mcp,api,server
Classifier: Development Status :: 4 - Beta
Classifier: Intended Audience :: Developers
Classifier: License :: OSI Approved :: MIT License
Classifier: Programming Language :: Python :: 3
Classifier: Programming Language :: Python :: 3.8
Classifier: Programming Language :: Python :: 3.9
Classifier: Programming Language :: Python :: 3.10
Classifier: Programming Language :: Python :: 3.11
Classifier: Programming Language :: Python :: 3.12
Classifier: Topic :: Software Development :: Libraries :: Python Modules
Requires-Python: >=3.10
License-File: LICENSE
Requires-Dist: duckdb>=1.2.1
Requires-Dist: mcp>=1.3.0
Requires-Dist: numpy>=2.2.3
Requires-Dist: pandas>=2.2.3
Requires-Dist: pyarrow>=19.0.1
Requires-Dist: requests>=2.28.0
Provides-Extra: dev
Requires-Dist: pytest>=7.0.0; extra == "dev"
Requires-Dist: black>=23.0.0; extra == "dev"
Requires-Dist: isort>=5.10.0; extra == "dev"
Requires-Dist: mypy>=1.0.0; extra == "dev"
Dynamic: license-file
